tree_sitter_orca/__init__.py
tree_sitter_orca/__init__.pyi
tree_sitter_orca/_binding.abi3.so
tree_sitter_orca/binding.c
tree_sitter_orca/py.typed
tree_sitter_orca/queries/folds.scm
tree_sitter_orca/queries/highlights.scm
tree_sitter_orca/queries/indents.scm
tree_sitter_orca-0.2.1.dist-info/METADATA
tree_sitter_orca-0.2.1.dist-info/WHEEL
tree_sitter_orca-0.2.1.dist-info/top_level.txt
tree_sitter_orca-0.2.1.dist-info/RECORD
