Metadata-Version: 2.4
Name: tree-sitter-orca
Version: 0.2.1
Summary: Parser for input file for the Orca quantum chemistry package
Author-email: Kalman Szenes <szenes.kalman@gmail.com>
License-Expression: MIT
Project-URL: Homepage, https://github.com/kszenes/tree-sitter-orca
Keywords: incremental,parsing,tree-sitter,orca
Classifier: Intended Audience :: Developers
Classifier: Topic :: Software Development :: Compilers
Classifier: Topic :: Text Processing :: Linguistic
Classifier: Typing :: Typed
Requires-Python: >=3.10
Requires-Dist: build>=1.3.0
Requires-Dist: twine>=6.1.0
Provides-Extra: core
Requires-Dist: tree-sitter~=0.24; extra == "core"
